{
    "consumes": [
        "application/json"
    ],
    "produces": [
        "application/json"
    ],
    "swagger": "2.0",
    "info": {
        "description": "A simple JWT powered API written in Go",
        "title": "Simple JWT API Go",
        "contact": {},
        "version": "1.0"
    },
    "host": "localhost:9000",
    "basePath": "/",
    "paths": {
        "/blacklist-access-token": {
            "post": {
                "security": [
                    {
                        "securitydefinitions.apikey": []
                    }
                ],
                "produces": [
                    "application/json"
                ],
                "summary": "Blacklist access token for user",
                "responses": {
                    "200": {
                        "description": "OK",
                        "schema": {
                            "allOf": [
                                {
                                    "$ref": "#/definitions/handlers.SuccessResponse"
                                },
                                {
                                    "type": "object",
                                    "properties": {
                                        "data": {
                                            "$ref": "#/definitions/handlers.BlankStruct"
                                        }
                                    }
                                }
                            ]
                        }
                    },
                    "400": {
                        "description": "Bad Request",
                        "schema": {
                            "$ref": "#/definitions/handlers.ErrorResponse"
                        }
                    },
                    "500": {
                        "description": "Internal Server Error",
                        "schema": {
                            "$ref": "#/definitions/handlers.ErrorResponse"
                        }
                    }
                }
            }
        },
        "/generate-access-token": {
            "post": {
                "consumes": [
                    "application/json"
                ],
                "produces": [
                    "application/json"
                ],
                "summary": "Generate access token for a new user",
                "parameters": [
                    {
                        "description": "body",
                        "name": "req",
                        "in": "body",
                        "required": true,
                        "schema": {
                            "$ref": "#/definitions/users.GenerateUserAccessTokenDTO"
                        }
                    }
                ],
                "responses": {
                    "200": {
                        "description": "OK",
                        "schema": {
                            "allOf": [
                                {
                                    "$ref": "#/definitions/handlers.SuccessResponse"
                                },
                                {
                                    "type": "object",
                                    "properties": {
                                        "data": {
                                            "allOf": [
                                                {
                                                    "$ref": "#/definitions/handlers.BlankStruct"
                                                },
                                                {
                                                    "type": "object",
                                                    "properties": {
                                                        "access_token": {
                                                            "type": "string"
                                                        },
                                                        "type": {
                                                            "type": "string"
                                                        },
                                                        "user": {
                                                            "$ref": "#/definitions/users.UserDTO"
                                                        }
                                                    }
                                                }
                                            ]
                                        }
                                    }
                                }
                            ]
                        }
                    },
                    "400": {
                        "description": "Bad Request",
                        "schema": {
                            "$ref": "#/definitions/handlers.ErrorResponse"
                        }
                    },
                    "500": {
                        "description": "Internal Server Error",
                        "schema": {
                            "$ref": "#/definitions/handlers.ErrorResponse"
                        }
                    }
                }
            }
        },
        "/me": {
            "get": {
                "security": [
                    {
                        "securitydefinitions.apikey": []
                    }
                ],
                "produces": [
                    "application/json"
                ],
                "summary": "Get authenticated user",
                "responses": {
                    "200": {
                        "description": "OK",
                        "schema": {
                            "allOf": [
                                {
                                    "$ref": "#/definitions/handlers.SuccessResponse"
                                },
                                {
                                    "type": "object",
                                    "properties": {
                                        "data": {
                                            "$ref": "#/definitions/users.UserDTO"
                                        }
                                    }
                                }
                            ]
                        }
                    },
                    "400": {
                        "description": "Bad Request",
                        "schema": {
                            "$ref": "#/definitions/handlers.ErrorResponse"
                        }
                    },
                    "500": {
                        "description": "Internal Server Error",
                        "schema": {
                            "$ref": "#/definitions/handlers.ErrorResponse"
                        }
                    }
                }
            }
        },
        "/register": {
            "post": {
                "consumes": [
                    "application/json"
                ],
                "produces": [
                    "application/json"
                ],
                "summary": "Register a new user",
                "parameters": [
                    {
                        "description": "body",
                        "name": "req",
                        "in": "body",
                        "required": true,
                        "schema": {
                            "$ref": "#/definitions/users.RegisterUserDTO"
                        }
                    }
                ],
                "responses": {
                    "200": {
                        "description": "OK",
                        "schema": {
                            "allOf": [
                                {
                                    "$ref": "#/definitions/handlers.SuccessResponse"
                                },
                                {
                                    "type": "object",
                                    "properties": {
                                        "data": {
                                            "$ref": "#/definitions/users.UserDTO"
                                        }
                                    }
                                }
                            ]
                        }
                    },
                    "400": {
                        "description": "Bad Request",
                        "schema": {
                            "$ref": "#/definitions/handlers.ErrorResponse"
                        }
                    },
                    "409": {
                        "description": "Conflict",
                        "schema": {
                            "$ref": "#/definitions/handlers.ErrorResponse"
                        }
                    },
                    "500": {
                        "description": "Internal Server Error",
                        "schema": {
                            "$ref": "#/definitions/handlers.ErrorResponse"
                        }
                    }
                }
            }
        }
    },
    "definitions": {
        "handlers.BlankStruct": {
            "type": "object"
        },
        "handlers.ErrorResponse": {
            "type": "object",
            "properties": {
                "code": {
                    "type": "integer"
                },
                "message": {
                    "type": "string"
                }
            }
        },
        "handlers.SuccessResponse": {
            "type": "object",
            "properties": {
                "code": {
                    "type": "integer"
                },
                "data": {}
            }
        },
        "users.GenerateUserAccessTokenDTO": {
            "type": "object",
            "required": [
                "email",
                "password"
            ],
            "properties": {
                "email": {
                    "type": "string"
                },
                "password": {
                    "type": "string"
                }
            }
        },
        "users.RegisterUserDTO": {
            "type": "object",
            "required": [
                "email",
                "name",
                "password"
            ],
            "properties": {
                "email": {
                    "type": "string"
                },
                "name": {
                    "type": "string"
                },
                "password": {
                    "type": "string",
                    "minLength": 6
                }
            }
        },
        "users.UserDTO": {
            "type": "object",
            "properties": {
                "email": {
                    "type": "string"
                },
                "id": {
                    "type": "string"
                },
                "name": {
                    "type": "string"
                }
            }
        }
    }
}